[
  {
    "message": "3 палки 1 люстра, палки активные",
    "date": 1534398220,
    "long": 37.44880844934069,
    "lat": 55.723333540817265
  },
  {
    "message": "одна люстра 2 палки",
    "date": 1534397991,
    "long": 37.51076503165561,
    "lat": 55.73525279759186
  },
  {
    "message": "На дублере одна палка ловит неугодных",
    "date": 1534397954,
    "long": 37.66742546042146,
    "lat": 55.69672603616114
  },
  {
    "message": "",
    "date": 1534397898,
    "long": 37.66617938468013,
    "lat": 55.690713656424336
  },
  {
    "message": "",
    "date": 1534397895,
    "long": 37.54375167227259,
    "lat": 55.7435783505202
  },
  {
    "message": "2 люстры, 5-6 палок, активные",
    "date": 1534395223,
    "long": 37.55559203061254,
    "lat": 55.56207118584434
  },
  {
    "message": "1 люстра, спит",
    "date": 1534392911,
    "long": 37.63984198276248,
    "lat": 55.732127320905334
  },
  {
    "message": "2 люстры неактивные",
    "date": 1534392758,
    "long": 37.58620673989675,
    "lat": 55.73822802861122
  },
  {
    "message": "2-3 экипажа, 3-4 палки. Активные",
    "date": 1534374716,
    "long": 37.62119500815894,
    "lat": 55.70551046564017
  },
  {
    "message": "внутренний мкад на носовиху в область, 2 люстры три палки актив",
    "date": 1534370272,
    "long": 37.83823544374291,
    "lat": 55.743707999877735
  },
  {
    "message": "2 люстры 1 палка без активности",
    "date": 1534370160,
    "long": 37.58449710165775,
    "lat": 55.84954547731512
  },
  {
    "message": "Съезд на трешку, активные.осторожно",
    "date": 1534368686,
    "long": 37.533999840256364,
    "lat": 55.73930072120669
  },
  {
    "message": "работают по такси",
    "date": 1534363079,
    "long": 37.57977303724809,
    "lat": 55.808811516727545
  },
  {
    "message": "Таксистов останавливают",
    "date": 1534345637,
    "long": 37.58598319803566,
    "lat": 55.86994935728364
  },
  {
    "message": "Экипаж, двое активные",
    "date": 1534344708,
    "long": 37.69672940459046,
    "lat": 55.782819715866815
  },
  {
    "message": "1 люстра 2 палки",
    "date": 1534344408,
    "long": 37.68185776015127,
    "lat": 55.78975320707329
  },
  {
    "message": "1 палка актив",
    "date": 1534343678,
    "long": 37.394786579079195,
    "lat": 55.75806997453315
  },
  {
    "message": "Одна люстра, две палки",
    "date": 1534342837,
    "long": 37.586449200466326,
    "lat": 55.89804436746229
  }
]